{    
    "type": "ForceProjector",
    "description": "A large shield projector that has much more health than a normal force projector",
    "localizedName": "Iron Dome",
    "health": 800,
    "shieldHealth": 8850,
    "size": 4,
    "liquidCapacity": 30,
    "hasPower": true,
    "canOverdrive": true,
    "phaseUseTime": 470,
    "phaseShieldBoost": 2000,
    "phaseRadiusBoost": 30,
    "solid": true,
    "radius": 161.7,
    "cooldownNormal": 1.25,
    "cooldownLiquid": 1.8,
    "cooldownBrokenBase": 0.6,
    "basePowerDraw": 5,
    "consumes": {
        "power": 18,
        "items": {
            "items": [
                "phase-fabric/2"
            ],
            "booster": true,
    	    "optional": true
        }
    },
    "requirements": [
        "osmium/220",
        "silicon/645",
        "titanium/595",
        "plastanium/820",
        "phase-fabric/755",
        "silicon/195"
    ],
    "category": "effect",
    "research": "force-projector"
}
