{
    "type": "ItemTurret",
    "description": "[acid]Fires three bullets that are made from radioactive materials that have different capabilities",
    "localizedName": "Tsar",
    "size": 7,
    "health": 280,
    "reloadTime": 65,
    "range": 300,
    "inaccuracy": 3,
    "shots": 3,
    "burstSpacing": 4,
    "targetAir": true,
    "targetGround": true,
    "shootCone": 0.08,
    "recoilAmount": 1.5,
    "restitution": 0.06,
    "rotateSpeed": 2,
    "shootSound": "shootBig",
    "ammoTypes": {
        "valvanite": {
        "type": "BasicBulletType",
        "speed": 5,
        "lifetime": 60,
        "status": "corroded",
        "statusDuration": 100,
        "damage": 70,
        "shootEffect": "shootBig",
        "knockback": 0.8,
        "height": 29,
        "width": 18,
		"frontColor":"7AC27CFF" ,
		"backColor": "468251FF",
        "despawnEffect": "plasticExplosionFlak",
        "hitEffect": "plasticExplosionFlak",
        "pierce": false,
        "smokeEffect": "none"
        },
        "thorium": {
        "type": "BasicBulletType",
        "speed": 5,
        "damage": 100,
        "lifetime": 60,
        "height": 29,
        "width": 18,
        "knockback": 2.4,
		"frontColor": "F9A3C7FF",
		"backColor": "CB8EBFFF",
        "shootEffect": "shootBig",
        "despawnEffect": "flakExplosion",
        "hitEffect": "flakExplosion",
        "pierce": true,
        "smokeEffect": "none"
        },
        "gamma-green": {
        "type": "BasicBulletType",
        "speed": 5,
        "damage": 164,
        "knockback": 0.8,
        "lifetime": 60,
        "splashDamageRadius": 20,
        "splashDamage": 50,
        "status": "slow",
        "statusDuration": 100,
        "height": 29,
        "width": 18,
        "frontColor": "C2FF70FF",
        "backColor": "739959FF",
        "shootEffect": "shootBig",
        "hitEffect": {
        "type": "ParticleEffect",
        "line": true,
        "particles": 7,
        "lifetime": 30,
        "length": 45,
        "offset": 4,
        "cone": 360,
        "lenFrom": 6,
        "lenTo": 0,
        "colorFrom": "C2FF70FF",
        "colorTo": "739959FF"
        },
        "despawnEffect": {
        "type": "ParticleEffect",
        "line": true,
        "particles": 7,
        "lifetime": 30,
        "length": 45,
        "offset": 4,
        "cone": 360,
        "lenFrom": 6,
        "lenTo": 0,
        "colorFrom": "C2FF70FF",
        "colorTo": "739959FF"
        },
        "pierce": false,
        "smokeEffect": "shootBigSmoke2"
        }
    },
    "requirements": [
        "thorium/400",
        "surge-alloy/370",
        "gamma-green/100",
        "titanium/400",
        "silicon/270",
        "graphite/600"
    ],
    "category": "turret",
    "research": "g-quarker"
}
